ancestree/__init__.py
ancestree/__main__.py
ancestree/dataset.py
ancestree/tools.py
tests/test_io.py
ancestree-0.1.0.dist-info/METADATA
ancestree-0.1.0.dist-info/WHEEL
ancestree-0.1.0.dist-info/top_level.txt
ancestree-0.1.0.dist-info/RECORD
