Metadata-Version: 2.4
Name: ancestree
Version: 0.1.0
Summary: A tool for merging and analyzing genealogy datasets.
Requires-Python: >=3.10
Requires-Dist: fire>=0.7.0
Provides-Extra: dev
Requires-Dist: pytest>=8.3.4; extra == "dev"
Requires-Dist: pytest-asyncio>=0.25.0; extra == "dev"
